README.rst
setup.py
stormbot_quizz/__init__.py
stormbot_quizz.egg-info/PKG-INFO
stormbot_quizz.egg-info/SOURCES.txt
stormbot_quizz.egg-info/dependency_links.txt
stormbot_quizz.egg-info/entry_points.txt
stormbot_quizz.egg-info/requires.txt
stormbot_quizz.egg-info/top_level.txt
stormbot_quizz/data/kaamelott.dic
stormbot_quizz/data/quizz.json