Metadata-Version: 1.1
Name: stormbot-quizz
Version: 1.0.0
Summary: quizz plugin for stormbot
Home-page: https://github.com/manoir/stormbot-quizz
Author: Paul Fariello
Author-email: paul@fariello.eu
License: UNKNOWN
Platform: UNKNOWN
Classifier: Environment :: Console
Classifier: Operating System :: POSIX
Classifier: Topic :: Communications :: Chat
Classifier: Programming Language :: Python
